galileoexperimentsextensions/__init__.py
galileoexperimentsextensions/gundetection/__init__.py
galileoexperimentsextensions/gundetection/app.py
galileoexperimentsextensions/gundetection/profiling/__init__.py
galileoexperimentsextensions/gundetection/profiling/main.py
galileoexperimentsextensions/humandetection/__init__.py
galileoexperimentsextensions/humandetection/app.py
galileoexperimentsextensions/humandetection/profiling/__init__.py
galileoexperimentsextensions/humandetection/profiling/main.py
galileoexperimentsextensions/maskdetection/__init__.py
galileoexperimentsextensions/maskdetection/app.py
galileoexperimentsextensions/maskdetection/profiling/__init__.py
galileoexperimentsextensions/maskdetection/profiling/main.py
galileoexperimentsextensions/maskdetection/scenario/__init__.py
galileoexperimentsextensions/maskdetection/scenario/main.py
galileoexperimentsextensions/mobilenet/__init__.py
galileoexperimentsextensions/mobilenet/app.py
galileoexperimentsextensions/mobilenet/util.py
galileoexperimentsextensions/mobilenet/profiling/__init__.py
galileoexperimentsextensions/mobilenet/profiling/main.py
galileoexperimentsextensions/mobilenet/scenario/__init__.py
galileoexperimentsextensions/mobilenet/scenario/main.py
galileoexperimentsextensions/objectdetection/__init__.py
galileoexperimentsextensions/objectdetection/app.py
galileoexperimentsextensions/objectdetection/profiling/__init__.py
galileoexperimentsextensions/objectdetection/profiling/main.py
galileoexperimentsextensions/poseestimation/__init__.py
galileoexperimentsextensions/poseestimation/app.py
galileoexperimentsextensions/poseestimation/profiling/__init__.py
galileoexperimentsextensions/poseestimation/profiling/main.py
galileoexperimentsextensions/sleepdetection/__init__.py
galileoexperimentsextensions/sleepdetection/app.py
galileoexperimentsextensions/sleepdetection/profiling/__init__.py
galileoexperimentsextensions/sleepdetection/profiling/main.py
edgerun_galileo_experiments_extensions-0.0.1.dev13.dist-info/LICENSE
edgerun_galileo_experiments_extensions-0.0.1.dev13.dist-info/METADATA
edgerun_galileo_experiments_extensions-0.0.1.dev13.dist-info/WHEEL
edgerun_galileo_experiments_extensions-0.0.1.dev13.dist-info/top_level.txt
edgerun_galileo_experiments_extensions-0.0.1.dev13.dist-info/RECORD
