Metadata-Version: 2.1
Name: edgerun-galileo-experiments-extensions
Version: 0.0.1.dev13
Summary: Galileo Experiments
Home-page: https://github.com/edgerun/galileo-experiments-extensions
Author: Philipp Raith
Author-email: p.raith@dsg.tuwien.ac.at
License: UNKNOWN
Platform: UNKNOWN
Classifier: Programming Language :: Python :: 3
Classifier: Operating System :: OS Independent
License-File: LICENSE
Requires-Dist: edgerun-galileo-experiments (>=0.0.2.dev9)
Requires-Dist: edgerun-request-generator (==1.0.0)
Requires-Dist: pandas (==1.4.3)
Requires-Dist: numpy (==1.22.3)
Requires-Dist: notebook (==6.4.10)
Requires-Dist: jupyter (==1.0.0)
Requires-Dist: jupyterlab (==3.3.2)
Requires-Dist: seaborn (==0.11.2)
Requires-Dist: matplotlib (==3.5.1)
